chromatic_matroids/__init__.py
chromatic_matroids/chromatic.py
chromatic_matroids/chromatic_statistics_matorids.py
chromatic_matroids/compositions.py
chromatic_matroids/generate_matroids_utils.py
chromatic_matroids/matrix_construction.py
chromatic_matroids/matroids.py
chromatic_matroids/ncquasisymmetric.py
chromatic_matroids/quasisymmetric.py
chromatic_matroids/setcompositions.py
chromatic_matroids/stable_matroids_setcompositions.py
chromatic_matroids/test_script.py
chromatic_matroids-0.0.3.dist-info/METADATA
chromatic_matroids-0.0.3.dist-info/WHEEL
chromatic_matroids-0.0.3.dist-info/licenses/LICENSE
chromatic_matroids-0.0.3.dist-info/RECORD
