Metadata-Version: 2.4
Name: chromatic_matroids
Version: 0.0.3
Summary: A package that exposes some matroid operation and creations
Project-URL: Homepage, https://github.com/raulpenaguiao/chromatic-matroids/tree/main/chromatic_matroids
Project-URL: Issues, https://github.com/raulpenaguiao/chromatic-matroids/tree/main/chromatic_matroids/issues
Author: Sophie Rehberg
Author-email: Raul Penaguiao <raul.penaguiao@proton.me>
License-Expression: MIT
License-File: LICENSE
Classifier: Operating System :: OS Independent
Classifier: Programming Language :: Python :: 3
Requires-Python: >=3.8
